lium_sdk.py
lium_sdk-0.2.12.dist-info/METADATA
lium_sdk-0.2.12.dist-info/WHEEL
lium_sdk-0.2.12.dist-info/top_level.txt
lium_sdk-0.2.12.dist-info/RECORD
