Metadata-Version: 2.4
Name: lium-sdk
Version: 0.2.12
Summary: A Python SDK for Lium API.
Author: Waris Ali
Project-URL: homepage, https://github.com/Datura-ai/lium-sdk
Project-URL: Repository, https://github.com/Datura-ai/lium-sdk
Requires-Python: >=3.9
Requires-Dist: pydantic>=2.0.0
Requires-Dist: httpx>=0.24.0
Requires-Dist: requests>=2.31.0
Requires-Dist: build>=0.10.0
Requires-Dist: loguru>=0.7.0
Requires-Dist: paramiko>=3.5.1
Requires-Dist: python-dotenv>=1.1.1
Requires-Dist: bittensor>=9.8.3
Provides-Extra: docs
Requires-Dist: mkdocstrings[python]>=0.24.0; extra == "docs"
Requires-Dist: mkdocs-material>=9.0.0; extra == "docs"
